{"ongoing_trials": {"tuner0": "0"}, "hyperparameters": {"space": [{"class_name": "Choice", "config": {"name": "densenet_version", "default": "DenseNet121", "conditions": [], "values": ["DenseNet121", "DenseNet169", "DenseNet201"], "ordered": false}}, {"class_name": "Choice", "config": {"name": "freeze_option", "default": "all", "conditions": [], "values": ["all", "partial", "none"], "ordered": false}}, {"class_name": "Int", "config": {"name": "num_dense_layers", "default": null, "conditions": [], "min_value": 1, "max_value": 3, "step": 1, "sampling": "linear"}}, {"class_name": "Int", "config": {"name": "dense_1_units", "default": null, "conditions": [], "min_value": 16, "max_value": 64, "step": 16, "sampling": "linear"}}, {"class_name": "Choice", "config": {"name": "dense_1_activation", "default": "relu", "conditions": [], "values": ["relu", "tanh", "elu"], "ordered": false}}, {"class_name": "Boolean", "config": {"name": "batch_norm_1", "default": false, "conditions": []}}, {"class_name": "Float", "config": {"name": "dropout_1_rate", "default": 0.2, "conditions": [], "min_value": 0.2, "max_value": 0.6, "step": 0.1, "sampling": "linear"}}, {"class_name": "Choice", "config": {"name": "optimizer", "default": "adam", "conditions": [], "values": ["adam", "rmsprop", "sgd"], "ordered": false}}, {"class_name": "Choice", "config": {"name": "learning_rate", "default": 0.01, "conditions": [], "values": [0.01, 0.001, 0.0001], "ordered": true}}], "values": {"densenet_version": "DenseNet121", "freeze_option": "all", "num_dense_layers": 1, "dense_1_units": 16, "dense_1_activation": "relu", "batch_norm_1": false, "dropout_1_rate": 0.2, "optimizer": "adam", "learning_rate": 0.01}}, "start_order": ["0"], "end_order": [], "run_times": {}, "retry_queue": [], "seed": 3502, "seed_state": 3511, "tried_so_far": ["92e153f47725249fff4a3532ccf8f2aa"], "id_to_hash": {"0": "92e153f47725249fff4a3532ccf8f2aa"}, "display": {"search_start": null, "trial_start": {}, "trial_number": {}}}